[{"id":438090356,"sampling_rate":null,"timestamp":"2017-10-29 01:45:29","location":{"id":1069,"latitude":"52.511","longitude":"13.424","country":"DE"},"sensor":{"id":2125,"pin":"1","sensor_type":{"id":14,"name":"SDS011","manufacturer":"Nova Fitness"}},"sensordatavalues":[{"id":970508056,"value":"4.60","value_type":"P1"}]},{"id":438090356,"sampling_rate":null,"timestamp":"2017-10-29 01:45:29","location":{"id":1069,"latitude":"52.511","longitude":"13.424","country":"DE"},"sensor":{"id":2125,"pin":"1","sensor_type":{"id":14,"name":"SDS011","manufacturer":"Nova Fitness"}},"sensordatavalues":[{"id":970508058,"value":"1.07","value_type":"P2"}]},{"id":438094817,"sampling_rate":null,"timestamp":"2017-10-29 01:47:55","location":{"id":1069,"latitude":"52.511","longitude":"13.424","country":"DE"},"sensor":{"id":2125,"pin":"1","sensor_type":{"id":14,"name":"SDS011","manufacturer":"Nova Fitness"}},"sensordatavalues":[{"id":970517468,"value":"2.13","value_type":"P1"},{"id":970517469,"value":"1.20","value_type":"P2"}]}]