[{"id":440400775,"sampling_rate":null,"timestamp":"2017-10-29 22:11:05","location":{"id":1069,"latitude":"52.511","longitude":"13.424","country":"DE"},"sensor":{"id":2125,"pin":"1","sensor_type":{"id":14,"name":"SDS011","manufacturer":"Nova Fitness"}},"sensordatavalues":[{"id":975381595,"value":"3.60","value_type":"P1"},{"id":975381596,"value":"1.67","value_type":"P2"}]},{"id":440405429,"sampling_rate":null,"timestamp":"2017-10-29 22:13:31","location":{"id":1069,"latitude":"52.511","longitude":"13.424","country":"DE"},"sensor":{"id":2125,"pin":"1","sensor_type":{"id":14,"name":"SDS011","manufacturer":"Nova Fitness"}},"sensordatavalues":[{"id":975391419,"value":"4.17","value_type":"P1"},{"id":975391420,"value":"1.30","value_type":"P2"}]}]