[{"id":439638319,"sampling_rate":null,"timestamp":"2017-10-29 15:28:08","location":{"id":1069,"latitude":"52.511","longitude":"13.424","country":"DE"},"sensor":{"id":2125,"pin":"1","sensor_type":{"id":14,"name":"SDS011","manufacturer":"Nova Fitness"}},"sensordatavalues":[{"id":973774485,"value":"1.87","value_type":"P1"},{"id":973774486,"value":"0.80","value_type":"P2"}]},{"id":439642952,"sampling_rate":null,"timestamp":"2017-10-29 15:30:34","location":{"id":1069,"latitude":"52.511","longitude":"13.424","country":"DE"},"sensor":{"id":2125,"pin":"1","sensor_type":{"id":14,"name":"SDS011","manufacturer":"Nova Fitness"}},"sensordatavalues":[{"id":973784237,"value":"2.30","value_type":"P1"},{"id":973784238,"value":"1.00","value_type":"P2"}]},{"id":439647573,"sampling_rate":null,"timestamp":"2017-10-29 15:33:00","location":{"id":1069,"latitude":"52.511","longitude":"13.424","country":"DE"},"sensor":{"id":2125,"pin":"1","sensor_type":{"id":14,"name":"SDS011","manufacturer":"Nova Fitness"}},"sensordatavalues":[{"id":973793976,"value":"2.28","value_type":"P1"},{"id":973793977,"value":"1.10","value_type":"P2"}]}]